{
    "슬라이드": [
        {"번호":"INTRO_S06_0001", "이미지":"0a8fe9ec-2ee0-495e-a6fc-b25de98e2d09.jpg","상품명":"[그린너트] 해바라기씨 1kg","할인율":0.07, "정가":6900, "후기":"252"},
        {"번호":"INTRO_S06_0002", "이미지":"0a54f6a4-4f5a-4202-8f6d-045d2a1709de.jpg","상품명":"[최현석의 쵸이닷] 새우 명란 오일 파스타","할인율":0.1, "정가":8900, "후기":"805"},
        {"번호":"INTRO_S06_0003", "이미지":"0b4697a8-c855-4987-b1c2-34d83d648098.jpg","상품명":"[부침명장] 깻잎전","할인율":0.1, "정가":9700, "후기":"999+"},
        {"번호":"INTRO_S06_0004", "이미지":"0d48bd99-0f96-4520-b37e-ef71097cb27f.jpg","상품명":"[연안식당] 해초국수 3입 (오리엔탈 소스 증정)","할인율":0.14, "정가":6900, "후기":"232"},
        {"번호":"INTRO_S06_0005", "이미지":"0d48bd99-0f96-4520-b37e-ef71097cb27f.jpg","상품명":"[연안식당] 해초국수 3입 (오리엔탈 소스 증정)","할인율":0.14, "정가":6900, "후기":"232"},
        {"번호":"INTRO_S06_0006", "이미지":"0d48bd99-0f96-4520-b37e-ef71097cb27f.jpg","상품명":"[연안식당] 해초국수 3입 (오리엔탈 소스 증정)","할인율":0.14, "정가":6900, "후기":"232"},
        {"번호":"INTRO_S06_0007", "이미지":"0d48bd99-0f96-4520-b37e-ef71097cb27f.jpg","상품명":"[연안식당] 해초국수 3입 (오리엔탈 소스 증정)","할인율":0.14, "정가":6900, "후기":"232"},
        {"번호":"INTRO_S06_0008", "이미지":"0d48bd99-0f96-4520-b37e-ef71097cb27f.jpg","상품명":"[연안식당] 해초국수 3입 (오리엔탈 소스 증정)","할인율":0.14, "정가":6900, "후기":"232"},
        {"번호":"INTRO_S06_0009", "이미지":"0d48bd99-0f96-4520-b37e-ef71097cb27f.jpg","상품명":"[연안식당] 해초국수 3입 (오리엔탈 소스 증정)","할인율":0.14, "정가":6900, "후기":"232"},
        {"번호":"INTRO_S06_0010", "이미지":"0d48bd99-0f96-4520-b37e-ef71097cb27f.jpg","상품명":"[연안식당] 해초국수 3입 (오리엔탈 소스 증정)","할인율":0.14, "정가":6900, "후기":"232"},
        {"번호":"INTRO_S06_0011", "이미지":"0d48bd99-0f96-4520-b37e-ef71097cb27f.jpg","상품명":"[연안식당] 해초국수 3입 (오리엔탈 소스 증정)","할인율":0.14, "정가":6900, "후기":"232"},
        {"번호":"INTRO_S06_0012", "이미지":"0d48bd99-0f96-4520-b37e-ef71097cb27f.jpg","상품명":"[연안식당] 해초국수 3입 (오리엔탈 소스 증정)","할인율":0.14, "정가":6900, "후기":"232"},
        {"번호":"INTRO_S06_0013", "이미지":"0d48bd99-0f96-4520-b37e-ef71097cb27f.jpg","상품명":"[연안식당] 해초국수 3입 (오리엔탈 소스 증정)","할인율":0.14, "정가":6900, "후기":"232"},
        {"번호":"INTRO_S06_0014", "이미지":"0d48bd99-0f96-4520-b37e-ef71097cb27f.jpg","상품명":"[연안식당] 해초국수 3입 (오리엔탈 소스 증정)","할인율":0.14, "정가":6900, "후기":"232"},
        {"번호":"INTRO_S06_0015", "이미지":"0d48bd99-0f96-4520-b37e-ef71097cb27f.jpg","상품명":"[연안식당] 해초국수 3입 (오리엔탈 소스 증정)","할인율":0.14, "정가":6900, "후기":"232"},
        {"번호":"INTRO_S06_0016", "이미지":"0d48bd99-0f96-4520-b37e-ef71097cb27f.jpg","상품명":"[연안식당] 해초국수 3입 (오리엔탈 소스 증정)","할인율":0.14, "정가":6900, "후기":"232"},
        {"번호":"INTRO_S06_0017", "이미지":"0d48bd99-0f96-4520-b37e-ef71097cb27f.jpg","상품명":"[연안식당] 해초국수 3입 (오리엔탈 소스 증정)","할인율":0.14, "정가":6900, "후기":"232"},
        {"번호":"INTRO_S06_0018", "이미지":"0d48bd99-0f96-4520-b37e-ef71097cb27f.jpg","상품명":"[연안식당] 해초국수 3입 (오리엔탈 소스 증정)","할인율":0.14, "정가":6900, "후기":"232"},
        {"번호":"INTRO_S06_0019", "이미지":"0d48bd99-0f96-4520-b37e-ef71097cb27f.jpg","상품명":"[연안식당] 해초국수 3입 (오리엔탈 소스 증정)","할인율":0.14, "정가":6900, "후기":"232"},
        {"번호":"INTRO_S06_0020", "이미지":"0d48bd99-0f96-4520-b37e-ef71097cb27f.jpg","상품명":"[연안식당] 해초국수 3입 (오리엔탈 소스 증정)","할인율":0.14, "정가":6900, "후기":"232"}
    ]
}